{"v":"5.6.6","ip":0,"op":1,"fr":60,"w":458,"h":114,"layers":[{"ind":369,"nm":"surface3336","ao":0,"ip":0,"op":60,"st":0,"ty":4,"ks":{"ty":"tr","o":{"k":100},"r":{"k":0},"p":{"k":[0,0]},"a":{"k":[0,0]},"s":{"k":[133.42,132.98]},"sk":{"k":0},"sa":{"k":0}},"shapes":[{"ty":"gr","hd":false,"nm":"surface3336","it":[{"ty":"gr","hd":false,"it":[{"ty":"sh","ks":{"k":{"i":[[0,0],[-2.85,-0.52],[-0.3,-1.57],[2.85,0.52],[0.3,1.58]],"o":[[-0.52,-2.85],[1.57,0.3],[0.52,2.85],[-1.57,-0.3],[0,0]],"v":[[233.85,28.27],[238.58,23.55],[241.73,26.7],[237,31.42],[233.85,28.27]],"c":true}}},{"ty":"fl","o":{"k":100},"c":{"k":[0.87,0.12,0.48,1]}},{"ty":"tr","o":{"k":100},"r":{"k":0},"p":{"k":[0,0]},"a":{"k":[0,0]},"s":{"k":[100,100]},"sk":{"k":0},"sa":{"k":0},"hd":false}]},{"ty":"gr","hd":false,"it":[{"ty":"sh","ks":{"k":{"i":[[0,0],[-2.85,-0.52],[-0.3,-1.57],[2.85,0.52],[0.3,1.58]],"o":[[-0.52,-2.85],[1.57,0.3],[0.52,2.85],[-1.57,-0.3],[0,0]],"v":[[99.75,55.65],[104.48,50.92],[107.62,54.07],[102.9,58.8],[99.75,55.65]],"c":true}}},{"ty":"fl","o":{"k":100},"c":{"k":[0.45,0.3,0.62,1]}},{"ty":"tr","o":{"k":100},"r":{"k":0},"p":{"k":[0,0]},"a":{"k":[0,0]},"s":{"k":[100,100]},"sk":{"k":0},"sa":{"k":0},"hd":false}]},{"ty":"gr","hd":false,"it":[{"ty":"sh","ks":{"k":{"i":[[0,0],[0.23,-0.52],[0.3,-0.38],[0.52,-0.22],[0.52,0],[0.45,0.23],[0.38,0.38],[0.15,0.53],[0,0.75],[-0.23,0.6],[-0.38,0.38],[-0.52,0.22],[-0.52,0],[-0.45,-0.23],[-0.38,-0.38],[-0.15,-0.53],[0,-0.68]],"o":[[0,0.68],[-0.23,0.52],[-0.38,0.38],[-0.52,0.23],[-0.52,0],[-0.45,-0.15],[-0.38,-0.38],[-0.23,-0.52],[0,-0.68],[0.23,-0.52],[0.38,-0.38],[0.45,-0.15],[0.52,0],[0.45,0.15],[0.38,0.38],[0.15,0.52],[0,0]],"v":[[96.98,55.73],[96.68,57.6],[95.85,58.95],[94.58,59.78],[93.08,60.08],[91.58,59.78],[90.3,58.95],[89.48,57.6],[89.18,55.73],[89.48,53.85],[90.38,52.5],[91.65,51.68],[93.15,51.38],[94.65,51.68],[95.93,52.5],[96.75,53.85],[96.98,55.73]],"c":true}}},{"ty":"sh","ks":{"k":{"i":[[0,0],[-0.07,-0.38],[-0.15,-0.22],[-0.3,-0.15],[-0.38,0],[-0.3,0.15],[-0.23,0.23],[-0.07,0.3],[0,0.45],[0.07,0.38],[0.15,0.22],[0.3,0.15],[0.38,0],[0.23,-0.15],[0.23,-0.23],[0.07,-0.3],[0,-0.45]],"o":[[0,0.45],[0.07,0.38],[0.23,0.23],[0.3,0.15],[0.38,0],[0.3,-0.15],[0.23,-0.23],[0.07,-0.3],[0,-0.45],[-0.07,-0.38],[-0.23,-0.23],[-0.3,-0.15],[-0.38,0],[-0.3,0.15],[-0.23,0.23],[-0.07,0.37],[0,0]],"v":[[90.6,55.73],[90.75,56.93],[91.2,57.82],[91.95,58.43],[92.93,58.65],[93.9,58.43],[94.65,57.82],[95.1,56.93],[95.25,55.73],[95.1,54.53],[94.65,53.63],[93.9,53.03],[92.93,52.8],[91.95,53.03],[91.2,53.63],[90.75,54.53],[90.6,55.73]],"c":true}}},{"ty":"fl","o":{"k":100},"c":{"k":[1,1,1,1]}},{"ty":"tr","o":{"k":100},"r":{"k":0},"p":{"k":[0,0]},"a":{"k":[0,0]},"s":{"k":[100,100]},"sk":{"k":0},"sa":{"k":0},"hd":false}]},{"ty":"gr","hd":false,"it":[{"ty":"sh","ks":{"k":{"i":[[0,0],[0.52,0.23],[0.3,0.38],[0.15,0.53],[0,0.68],[-0.23,0.53],[-0.3,0.38],[-0.52,0.15],[-0.6,0],[-0.22,-0.07],[-0.23,-0.07],[-0.15,-0.08],[-0.07,0],[0,0],[0.38,0.07],[0.38,0],[0.3,-0.07],[0.22,-0.22],[0.15,-0.38],[0,-0.45],[-0.07,-0.38],[-0.22,-0.22],[-0.3,-0.15],[-0.45,0],[-0.3,0.07],[-0.15,0.07],[0,0],[0.15,0],[0.23,0],[0.3,-0.07],[0.3,0]],"o":[[-0.6,0],[-0.45,-0.23],[-0.3,-0.38],[-0.15,-0.52],[0,-0.68],[0.23,-0.52],[0.38,-0.38],[0.45,-0.15],[0.3,0],[0.3,0.07],[0.23,0.07],[0.15,0.07],[0,0],[-0.23,-0.15],[-0.38,-0.07],[-0.38,0],[-0.3,0.15],[-0.23,0.23],[-0.15,0.38],[0,0.45],[0.07,0.38],[0.23,0.3],[0.3,0.15],[0.52,0],[0.3,-0.07],[0,0],[-0.07,0.07],[-0.15,0.07],[-0.23,0.07],[-0.14,0.24],[0,0]],"v":[[85.5,60],[83.85,59.7],[82.65,58.88],[81.9,57.52],[81.6,55.72],[81.9,53.92],[82.73,52.57],[84,51.75],[85.57,51.45],[86.47,51.52],[87.22,51.67],[87.75,51.89],[88.05,52.04],[87.6,53.24],[86.77,52.94],[85.65,52.79],[84.67,52.94],[83.85,53.46],[83.32,54.36],[83.1,55.64],[83.25,56.84],[83.7,57.73],[84.45,58.34],[85.57,58.56],[86.84,58.41],[87.59,58.11],[87.97,59.31],[87.59,59.46],[86.99,59.61],[86.24,59.76],[85.5,60]],"c":true}}},{"ty":"fl","o":{"k":100},"c":{"k":[1,1,1,1]}},{"ty":"tr","o":{"k":100},"r":{"k":0},"p":{"k":[0,0]},"a":{"k":[0,0]},"s":{"k":[100,100]},"sk":{"k":0},"sa":{"k":0},"hd":false}]},{"ty":"gr","hd":false,"it":[{"ty":"sh","ks":{"k":{"i":[[0,0],[0,0],[0,0],[0,0]],"o":[[0,0],[0,0],[0,0],[0,0]],"v":[[78.45,51.68],[79.95,51.68],[79.95,59.85],[78.45,59.85]],"c":true}}},{"ty":"fl","o":{"k":100},"c":{"k":[1,1,1,1]}},{"ty":"tr","o":{"k":100},"r":{"k":0},"p":{"k":[0,0]},"a":{"k":[0,0]},"s":{"k":[100,100]},"sk":{"k":0},"sa":{"k":0},"hd":false}]},{"ty":"gr","hd":false,"it":[{"ty":"sh","ks":{"k":{"i":[[0,0],[0,0],[0,0],[0,0],[0,0],[0,0]],"o":[[0,0],[0,0],[0,0],[0,0],[0,0],[0,0]],"v":[[77.32,58.5],[77.32,59.77],[72.15,59.77],[72.15,51.68],[73.65,51.68],[73.65,58.5]],"c":true}}},{"ty":"fl","o":{"k":100},"c":{"k":[1,1,1,1]}},{"ty":"tr","o":{"k":100},"r":{"k":0},"p":{"k":[0,0]},"a":{"k":[0,0]},"s":{"k":[100,100]},"sk":{"k":0},"sa":{"k":0},"hd":false}]},{"ty":"gr","hd":false,"it":[{"ty":"sh","ks":{"k":{"i":[[0,0],[0.38,0.07],[0.3,0.07],[0,0],[-0.15,0],[-0.23,0],[-0.23,0],[-0.23,0],[-0.38,-0.07],[-0.3,-0.15],[-0.23,-0.3],[0,-0.45],[0.23,-0.23],[0.3,-0.15],[-0.3,-0.38],[0,-0.45],[0.6,-0.38],[1.28,0]],"o":[[-0.45,0],[-0.45,0],[0,0],[0.15,0],[0.23,0],[0.23,0],[0.23,0],[0.52,0],[0.38,0.07],[0.3,0.15],[0.15,0.3],[0,0.38],[-0.15,0.3],[0.52,0.15],[0.23,0.3],[0,0.82],[-0.68,0.45],[0,0]],"v":[[66.9,59.93],[65.62,59.85],[64.5,59.7],[64.5,51.75],[65.02,51.68],[65.62,51.6],[66.23,51.6],[66.83,51.6],[68.18,51.68],[69.3,52.05],[70.05,52.73],[70.28,53.78],[69.98,54.75],[69.23,55.43],[70.36,56.18],[70.73,57.38],[69.83,59.25],[66.9,59.93]],"c":true}}},{"ty":"sh","ks":{"k":{"i":[[0,0],[0,0],[-0.38,0.15],[0,0.45],[0.38,0.15],[0.52,0],[0.15,0],[0.15,0]],"o":[[0,0],[0.6,0],[0.3,-0.15],[0,-0.38],[-0.3,-0.15],[-0.23,0],[-0.15,0],[0,0]],"v":[[65.93,54.98],[66.98,54.98],[68.33,54.75],[68.78,53.85],[68.25,53.03],[66.98,52.8],[66.38,52.8],[65.93,52.8]],"c":true}}},{"ty":"sh","ks":{"k":{"i":[[0,0],[0,0],[-0.15,0],[-0.15,0],[-0.22,0.07],[-0.15,0.15],[-0.07,0.15],[0,0.23],[0.38,0.23],[0.6,0],[0,0]],"o":[[0,0],[0.15,0],[0.23,0],[0.3,0],[0.3,-0.07],[0.15,-0.15],[0.15,-0.15],[0,-0.45],[-0.38,-0.23],[0,0],[0,0]],"v":[[65.93,56.18],[65.93,58.65],[66.45,58.65],[66.97,58.65],[67.8,58.58],[68.47,58.35],[68.92,57.98],[69.07,57.38],[68.55,56.4],[67.12,56.1],[65.93,56.1]],"c":true}}},{"ty":"fl","o":{"k":100},"c":{"k":[1,1,1,1]}},{"ty":"tr","o":{"k":100},"r":{"k":0},"p":{"k":[0,0]},"a":{"k":[0,0]},"s":{"k":[100,100]},"sk":{"k":0},"sa":{"k":0},"hd":false}]},{"ty":"gr","hd":false,"it":[{"ty":"sh","ks":{"k":{"i":[[0,0],[0.38,0.15],[0.23,0.3],[0.15,0.45],[0,0.45],[0,0],[0,0],[0,0],[-0.07,-0.3],[-0.15,-0.23],[-0.22,-0.07],[-0.23,0],[-0.15,0.07],[-0.15,0.15],[-0.07,0.3],[0,0.38],[0,0],[0,0],[0,0],[0.15,-0.38],[0.3,-0.3],[0.38,-0.15],[0.6,0]],"o":[[-0.52,0],[-0.38,-0.15],[-0.3,-0.3],[-0.15,-0.38],[0,0],[0,0],[0,0],[0,0.38],[0.07,0.3],[0.15,0.15],[0.23,0.07],[0.23,0],[0.15,-0.07],[0.15,-0.15],[0.07,-0.23],[0,0],[0,0],[0,0],[0,0.45],[-0.15,0.38],[-0.3,0.3],[-0.36,0.15],[0,0]],"v":[[59.32,60],[57.9,59.77],[56.92,59.1],[56.32,58.05],[56.09,56.77],[56.09,51.67],[57.59,51.67],[57.59,56.62],[57.74,57.6],[58.12,58.27],[58.64,58.65],[59.32,58.8],[59.99,58.65],[60.52,58.27],[60.89,57.6],[61.04,56.62],[61.04,51.67],[62.54,51.67],[62.54,56.77],[62.31,58.05],[61.71,59.1],[60.73,59.77],[59.32,60]],"c":true}}},{"ty":"sh","ks":{"k":{"i":[[0,0],[0,0],[0,0],[0,0]],"o":[[0,0],[0,0],[0,0],[0,0]],"v":[[61.35,49.27],[59.4,51.15],[58.73,50.55],[60.45,48.52]],"c":true}}},{"ty":"fl","o":{"k":100},"c":{"k":[1,1,1,1]}},{"ty":"tr","o":{"k":100},"r":{"k":0},"p":{"k":[0,0]},"a":{"k":[0,0]},"s":{"k":[100,100]},"sk":{"k":0},"sa":{"k":0},"hd":false}]},{"ty":"gr","hd":false,"it":[{"ty":"sh","ks":{"k":{"i":[[0,0],[-0.6,-0.45],[0,-0.9],[0.15,-0.3],[0.3,-0.22],[0.45,-0.07],[0.6,0],[0,0],[0,0],[0,0],[0,0],[-0.38,0],[-0.3,0]],"o":[[1.2,0],[0.6,0.45],[0,0.45],[-0.15,0.38],[-0.3,0.23],[-0.45,0.07],[0,0],[0,0],[0,0],[0,0],[0.38,-0.07],[0.53,0],[0,0]],"v":[[51.15,51.6],[53.85,52.28],[54.82,54.3],[54.6,55.5],[53.85,56.32],[52.65,56.77],[51.07,56.92],[50.32,56.92],[50.32,59.77],[48.82,59.77],[48.82,51.75],[49.95,51.6],[51.15,51.6]],"c":true}}},{"ty":"sh","ks":{"k":{"i":[[0,0],[0.22,0],[0,0],[0,0],[-0.38,0.23],[0,0.52],[0.07,0.15],[0.22,0.15],[0.3,0.08],[0.3,0]],"o":[[-0.38,0],[0,0],[0,0],[0.75,0],[0.38,-0.23],[0,-0.3],[-0.07,-0.15],[-0.15,-0.07],[-0.3,-0.07],[0,0]],"v":[[51.3,52.88],[50.4,52.88],[50.4,55.65],[51.15,55.65],[52.8,55.35],[53.4,54.22],[53.25,53.55],[52.8,53.1],[52.13,52.87],[51.3,52.88]],"c":true}}},{"ty":"fl","o":{"k":100},"c":{"k":[1,1,1,1]}},{"ty":"tr","o":{"k":100},"r":{"k":0},"p":{"k":[0,0]},"a":{"k":[0,0]},"s":{"k":[100,100]},"sk":{"k":0},"sa":{"k":0},"hd":false}]},{"ty":"gr","hd":false,"it":[{"ty":"sh","ks":{"k":{"i":[[0,0],[-0.6,-0.45],[0,-0.82],[1.12,-0.38],[-0.22,-0.3],[-0.23,-0.3],[-0.23,-0.3],[-0.07,-0.3],[0,0],[0.15,0.22],[0.15,0.22],[0.15,0.23],[0.15,0.23],[0.07,0],[0.08,0],[0,0],[0,0],[0,0],[0,0],[-0.38,0],[-0.3,0]],"o":[[1.2,0],[0.6,0.45],[0,1.12],[0.15,0.15],[0.23,0.23],[0.23,0.3],[0.15,0.3],[0,0],[-0.15,-0.3],[-0.15,-0.3],[-0.15,-0.3],[-0.15,-0.23],[-0.07,0],[-0.07,0],[0,0],[0,0],[0,0],[0,0],[0.38,-0.07],[0.45,0],[0,0]],"v":[[40.88,51.6],[43.57,52.28],[44.47,54.23],[42.82,56.48],[43.35,57.15],[43.95,57.98],[44.55,58.88],[45,59.77],[43.35,59.77],[42.9,58.95],[42.38,58.12],[41.86,57.38],[41.41,56.7],[41.11,56.7],[40.88,56.7],[40.13,56.7],[40.13,59.77],[38.63,59.77],[38.62,51.75],[39.75,51.6],[40.88,51.6]],"c":true}}},{"ty":"sh","ks":{"k":{"i":[[0,0],[0.3,0],[0,0],[0,0],[-0.3,0.07],[-0.15,0.15],[-0.15,0.15],[0,0.3],[0.07,0.15],[0.15,0.07],[0.23,0.08],[0.3,0]],"o":[[-0.3,0],[0,0],[0,0],[0.38,0],[0.3,-0.07],[0.15,-0.15],[0.07,-0.15],[0,-0.23],[-0.07,-0.15],[-0.15,-0.07],[-0.3,-0.07],[0,0]],"v":[[40.95,52.88],[40.05,52.88],[40.05,55.5],[40.73,55.5],[41.7,55.43],[42.38,55.2],[42.83,54.82],[42.98,54.15],[42.83,53.55],[42.45,53.17],[41.85,52.95],[40.95,52.88]],"c":true}}},{"ty":"fl","o":{"k":100},"c":{"k":[1,1,1,1]}},{"ty":"tr","o":{"k":100},"r":{"k":0},"p":{"k":[0,0]},"a":{"k":[0,0]},"s":{"k":[100,100]},"sk":{"k":0},"sa":{"k":0},"hd":false}]},{"ty":"gr","hd":false,"it":[{"ty":"sh","ks":{"k":{"i":[[0,0],[0.23,-0.52],[0.3,-0.38],[0.52,-0.22],[0.52,0],[0.45,0.23],[0.38,0.38],[0.15,0.53],[0,0.75],[-0.23,0.6],[-0.38,0.38],[-0.52,0.22],[-0.52,0],[-0.45,-0.23],[-0.38,-0.38],[-0.15,-0.53],[0,-0.68]],"o":[[0,0.68],[-0.23,0.52],[-0.38,0.38],[-0.52,0.23],[-0.52,0],[-0.45,-0.15],[-0.38,-0.38],[-0.23,-0.52],[0,-0.68],[0.23,-0.52],[0.38,-0.38],[0.45,-0.15],[0.52,0],[0.45,0.15],[0.38,0.38],[0.15,0.52],[0,0]],"v":[[36.98,55.73],[36.68,57.6],[35.85,58.95],[34.58,59.78],[33.08,60.08],[31.58,59.78],[30.3,58.95],[29.48,57.6],[29.18,55.73],[29.48,53.85],[30.38,52.5],[31.65,51.68],[33.15,51.38],[34.65,51.68],[35.93,52.5],[36.75,53.85],[36.98,55.73]],"c":true}}},{"ty":"sh","ks":{"k":{"i":[[0,0],[-0.07,-0.38],[-0.15,-0.22],[-0.3,-0.15],[-0.38,0],[-0.3,0.15],[-0.23,0.23],[-0.07,0.3],[0,0.45],[0.07,0.38],[0.15,0.22],[0.3,0.15],[0.38,0],[0.23,-0.15],[0.23,-0.23],[0.07,-0.3],[0,-0.45]],"o":[[0,0.45],[0.07,0.38],[0.23,0.23],[0.3,0.15],[0.38,0],[0.3,-0.15],[0.23,-0.23],[0.07,-0.3],[0,-0.45],[-0.07,-0.38],[-0.23,-0.23],[-0.3,-0.15],[-0.38,0],[-0.3,0.15],[-0.23,0.23],[-0.15,0.37],[0,0]],"v":[[30.68,55.73],[30.82,56.93],[31.27,57.82],[32.02,58.43],[33,58.65],[33.98,58.43],[34.73,57.82],[35.18,56.93],[35.32,55.73],[35.18,54.53],[34.73,53.63],[33.98,53.03],[33,52.8],[32.02,53.03],[31.27,53.63],[30.82,54.53],[30.68,55.73]],"c":true}}},{"ty":"fl","o":{"k":100},"c":{"k":[1,1,1,1]}},{"ty":"tr","o":{"k":100},"r":{"k":0},"p":{"k":[0,0]},"a":{"k":[0,0]},"s":{"k":[100,100]},"sk":{"k":0},"sa":{"k":0},"hd":false}]},{"ty":"gr","hd":false,"it":[{"ty":"sh","ks":{"k":{"i":[[0,0],[0,0],[0,0],[0,0],[0,0],[0,0],[0,0],[0,0]],"o":[[0,0],[0,0],[0,0],[0,0],[0,0],[0,0],[0,0],[0,0]],"v":[[28.27,51.68],[28.27,52.95],[25.8,52.95],[25.8,59.85],[24.3,59.85],[24.3,52.95],[21.82,52.95],[21.82,51.68]],"c":true}}},{"ty":"fl","o":{"k":100},"c":{"k":[1,1,1,1]}},{"ty":"tr","o":{"k":100},"r":{"k":0},"p":{"k":[0,0]},"a":{"k":[0,0]},"s":{"k":[100,100]},"sk":{"k":0},"sa":{"k":0},"hd":false}]},{"ty":"gr","hd":false,"it":[{"ty":"sh","ks":{"k":{"i":[[0,0],[0,0],[0,0],[0,0],[0,0],[0,0],[0,0],[0,0],[0,0],[0,0],[0,0],[0,0],[0,0]],"o":[[0,0],[0,0],[0,0],[0,0],[0,0],[0,0],[0,0],[0,0],[0,0],[0,0],[0,0],[0,0],[0,0]],"v":[[15.75,59.77],[15.75,51.68],[21,51.68],[21,52.95],[17.25,52.95],[17.25,54.97],[20.55,54.97],[20.55,56.17],[17.25,56.18],[17.25,58.57],[21.3,58.57],[21.3,59.85],[15.75,59.85]],"c":true}}},{"ty":"fl","o":{"k":100},"c":{"k":[1,1,1,1]}},{"ty":"tr","o":{"k":100},"r":{"k":0},"p":{"k":[0,0]},"a":{"k":[0,0]},"s":{"k":[100,100]},"sk":{"k":0},"sa":{"k":0},"hd":false}]},{"ty":"gr","hd":false,"it":[{"ty":"sh","ks":{"k":{"i":[[0,0],[-0.3,0.23],[0,0.3],[0.07,0.15],[0.15,0.07],[0.15,0.07],[0.3,0.07],[0.3,0.07],[0.15,0.15],[0.07,0.3],[0,0.38],[-0.52,0.38],[-0.9,0],[-0.38,-0.07],[-0.22,-0.15],[0,0],[0.38,0.15],[0.3,0],[0.22,-0.15],[0,-0.3],[-0.07,-0.15],[-0.15,-0.15],[-0.15,-0.07],[-0.23,-0.08],[-0.3,-0.15],[-0.23,-0.22],[-0.07,-0.23],[0,-0.38],[0.52,-0.45],[0.98,0],[0.22,0.07],[0.23,0.07],[0.15,0.08],[0.07,0],[0,0],[-0.3,-0.15],[-0.52,0]],"o":[[0.52,0],[0.3,-0.23],[0,-0.23],[-0.07,-0.15],[-0.15,-0.15],[-0.23,-0.07],[-0.3,-0.07],[-0.3,-0.07],[-0.23,-0.15],[-0.15,-0.23],[0,-0.75],[0.52,-0.45],[0.52,0],[0.38,0.07],[0,0],[-0.3,-0.15],[-0.3,-0.07],[-0.38,0],[-0.23,0.15],[0,0.15],[0.07,0.15],[0.15,0.15],[0.15,0.07],[0.38,0.15],[0.3,0.15],[0.23,0.23],[0.07,0.3],[0,0.75],[-0.52,0.38],[-0.3,0],[-0.3,-0.07],[-0.23,-0.07],[-0.15,-0.07],[0,0],[0.23,0.15],[0.22,0.14],[0,0]],"v":[[11.4,58.73],[12.6,58.43],[12.97,57.68],[12.82,57.15],[12.45,56.78],[11.93,56.48],[11.18,56.18],[10.35,55.88],[9.68,55.43],[9.23,54.75],[9.08,53.85],[9.83,52.12],[11.93,51.52],[13.28,51.67],[14.18,52.05],[13.73,53.25],[12.83,52.87],[11.86,52.72],[10.96,52.95],[10.66,53.62],[10.73,54.07],[11.03,54.45],[11.48,54.75],[12.08,54.98],[13.13,55.43],[13.88,55.95],[14.33,56.62],[14.48,57.6],[13.73,59.33],[11.48,59.93],[10.58,59.86],[9.83,59.71],[9.31,59.48],[8.93,59.33],[9.38,58.13],[10.21,58.51],[11.4,58.73]],"c":true}}},{"ty":"fl","o":{"k":100},"c":{"k":[1,1,1,1]}},{"ty":"tr","o":{"k":100},"r":{"k":0},"p":{"k":[0,0]},"a":{"k":[0,0]},"s":{"k":[100,100]},"sk":{"k":0},"sa":{"k":0},"hd":false}]},{"ty":"gr","hd":false,"it":[{"ty":"sh","ks":{"k":{"i":[[0,0],[0.23,-0.6],[0.3,-0.38],[0.52,-0.22],[0.52,0],[0.45,0.23],[0.38,0.38],[0.15,0.53],[0,0.75],[-0.23,0.6],[-0.38,0.38],[-0.52,0.22],[-0.52,0],[-0.45,-0.23],[-0.38,-0.38],[-0.15,-0.53],[0,-0.68]],"o":[[0,0.68],[-0.23,0.52],[-0.38,0.38],[-0.45,0.15],[-0.52,0],[-0.45,-0.23],[-0.38,-0.38],[-0.23,-0.52],[0,-0.75],[0.23,-0.52],[0.38,-0.38],[0.45,-0.15],[0.52,0],[0.45,0.15],[0.38,0.38],[0.07,0.6],[0,0]],"v":[[335.48,28.05],[335.18,29.93],[334.35,31.28],[333.08,32.1],[331.58,32.4],[330.08,32.1],[328.8,31.28],[327.98,29.93],[327.68,28.05],[327.98,26.18],[328.88,24.82],[330.15,24],[331.65,23.7],[333.15,24],[334.43,24.82],[335.25,26.18],[335.48,28.05]],"c":true}}},{"ty":"sh","ks":{"k":{"i":[[0,0],[-0.07,-0.38],[-0.15,-0.22],[-0.3,-0.15],[-0.38,0],[-0.3,0.15],[-0.23,0.23],[-0.07,0.3],[0,0.45],[0.07,0.38],[0.15,0.22],[0.3,0.15],[0.38,0],[0.23,-0.15],[0.23,-0.23],[0.07,-0.3],[0,-0.38]],"o":[[0,0.45],[0.07,0.38],[0.23,0.23],[0.3,0.15],[0.38,0],[0.3,-0.15],[0.23,-0.23],[0.07,-0.3],[0,-0.45],[-0.07,-0.38],[-0.23,-0.23],[-0.3,-0.15],[-0.38,0],[-0.3,0.15],[-0.23,0.23],[-0.07,0.3],[0,0]],"v":[[329.1,28.05],[329.25,29.25],[329.7,30.15],[330.45,30.75],[331.43,30.98],[332.4,30.75],[333.15,30.15],[333.6,29.25],[333.75,28.05],[333.6,26.85],[333.15,25.95],[332.4,25.35],[331.43,25.12],[330.45,25.35],[329.7,25.95],[329.25,26.85],[329.1,28.05]],"c":true}}},{"ty":"fl","o":{"k":100},"c":{"k":[1,1,1,1]}},{"ty":"tr","o":{"k":100},"r":{"k":0},"p":{"k":[0,0]},"a":{"k":[0,0]},"s":{"k":[100,100]},"sk":{"k":0},"sa":{"k":0},"hd":false}]},{"ty":"gr","hd":false,"it":[{"ty":"sh","ks":{"k":{"i":[[0,0],[0.23,-0.52],[0.38,-0.3],[0.53,-0.15],[0.68,0],[0.45,0.07],[0.38,0.07],[0,0],[-0.45,0],[-0.3,0],[-0.6,-0.15],[-0.38,-0.38],[-0.15,-0.52],[0,-0.68]],"o":[[0,0.68],[-0.23,0.52],[-0.38,0.3],[-0.6,0.15],[-0.3,0],[-0.45,-0.07],[0,0],[0.38,-0.07],[0.45,0],[0.68,0],[0.6,0.15],[0.38,0.38],[0.23,0.52],[0,0]],"v":[[326.25,28.05],[325.95,29.93],[325.05,31.2],[323.62,31.95],[321.75,32.18],[320.62,32.1],[319.43,31.95],[319.43,24.15],[320.62,24],[321.75,24],[323.62,24.23],[325.05,24.98],[325.95,26.25],[326.25,28.05]],"c":true}}},{"ty":"sh","ks":{"k":{"i":[[0,0],[-0.15,0],[-0.3,0],[-0.52,0.52],[0,0.9],[0.52,0.45],[1.05,0],[0.23,0]],"o":[[0.07,0],[0.15,0],[0.98,0],[0.52,-0.52],[0,-0.9],[-0.45,-0.52],[-0.45,0],[0,0]],"v":[[320.85,30.98],[321.23,30.98],[321.83,30.98],[324.08,30.23],[324.83,28.12],[324.08,26.02],[321.83,25.27],[320.85,25.27]],"c":true}}},{"ty":"fl","o":{"k":100},"c":{"k":[1,1,1,1]}},{"ty":"tr","o":{"k":100},"r":{"k":0},"p":{"k":[0,0]},"a":{"k":[0,0]},"s":{"k":[100,100]},"sk":{"k":0},"sa":{"k":0},"hd":false}]},{"ty":"gr","hd":false,"it":[{"ty":"sh","ks":{"k":{"i":[[0,0],[0.15,0.3],[0.15,0.38],[0,0],[0.07,-0.3],[0.07,-0.38],[0,0],[-0.3,0.75],[-0.3,0.68],[-0.23,0.6],[-0.3,0.6],[0,0],[-0.3,-0.6],[-0.23,-0.68],[-0.3,-0.75],[-0.3,-0.82]],"o":[[-0.07,-0.3],[-0.15,-0.3],[0,0],[-0.07,0.3],[-0.15,0.3],[0,0],[0.3,-0.9],[0.3,-0.75],[0.3,-0.68],[0.23,-0.6],[0,0],[0.3,0.6],[0.23,0.6],[0.3,0.68],[0.3,0.75],[0,0]],"v":[[316.73,32.18],[316.35,31.2],[315.98,30.22],[312.53,30.22],[312.23,31.2],[311.93,32.18],[310.35,32.18],[311.25,29.78],[312.07,27.68],[312.82,25.8],[313.65,24],[315.07,24],[315.9,25.8],[316.65,27.68],[317.47,29.78],[318.37,32.18]],"c":true}}},{"ty":"sh","ks":{"k":{"i":[[0,0],[0.23,-0.6],[0.3,-0.68],[0,0],[0.23,0.6],[0.15,0.45]],"o":[[-0.15,0.45],[-0.23,0.6],[0,0],[-0.23,-0.68],[-0.22,-0.6],[0,0]],"v":[[314.32,25.57],[313.72,27.07],[312.97,29.02],[315.67,29.02],[314.92,27.07],[314.32,25.57]],"c":true}}},{"ty":"fl","o":{"k":100},"c":{"k":[1,1,1,1]}},{"ty":"tr","o":{"k":100},"r":{"k":0},"p":{"k":[0,0]},"a":{"k":[0,0]},"s":{"k":[100,100]},"sk":{"k":0},"sa":{"k":0},"hd":false}]},{"ty":"gr","hd":false,"it":[{"ty":"sh","ks":{"k":{"i":[[0,0],[0.6,1.35],[0.45,1.35],[0,0],[-0.23,-0.52],[-0.23,-0.52],[-0.23,-0.52],[-0.23,-0.45],[-0.23,0.53],[-0.23,0.52],[-0.23,0.6],[-0.23,0.52],[0,0],[0.52,-1.35],[0.6,-1.28],[0,0]],"o":[[-0.6,-1.27],[-0.52,-1.35],[0,0],[0.23,0.52],[0.23,0.6],[0.23,0.52],[0.23,0.52],[0.15,-0.45],[0.23,-0.52],[0.23,-0.52],[0.23,-0.6],[0,0],[-0.45,1.35],[-0.52,1.35],[0,0],[0,0]],"v":[[305.62,32.18],[303.9,28.2],[302.4,24.07],[304.05,24.07],[304.65,25.72],[305.25,27.37],[305.85,28.95],[306.45,30.37],[307.05,28.95],[307.66,27.37],[308.26,25.64],[308.86,24],[310.43,24],[308.93,28.12],[307.21,32.1],[305.62,32.1]],"c":true}}},{"ty":"fl","o":{"k":100},"c":{"k":[1,1,1,1]}},{"ty":"tr","o":{"k":100},"r":{"k":0},"p":{"k":[0,0]},"a":{"k":[0,0]},"s":{"k":[100,100]},"sk":{"k":0},"sa":{"k":0},"hd":false}]},{"ty":"gr","hd":false,"it":[{"ty":"sh","ks":{"k":{"i":[[0,0],[0,0],[0,0],[0,0]],"o":[[0,0],[0,0],[0,0],[0,0]],"v":[[299.85,24],[301.35,24],[301.35,32.18],[299.85,32.18]],"c":true}}},{"ty":"fl","o":{"k":100},"c":{"k":[1,1,1,1]}},{"ty":"tr","o":{"k":100},"r":{"k":0},"p":{"k":[0,0]},"a":{"k":[0,0]},"s":{"k":[100,100]},"sk":{"k":0},"sa":{"k":0},"hd":false}]},{"ty":"gr","hd":false,"it":[{"ty":"sh","ks":{"k":{"i":[[0,0],[-0.6,-0.45],[0,-0.82],[1.12,-0.38],[-0.22,-0.3],[-0.23,-0.3],[-0.23,-0.3],[-0.07,-0.3],[0,0],[0.15,0.22],[0.15,0.22],[0.15,0.23],[0.15,0.23],[0.07,0],[0.08,0],[0,0],[0,0],[0,0],[0,0],[-0.38,0],[-0.3,0]],"o":[[1.2,0],[0.6,0.45],[0,1.12],[0.15,0.15],[0.23,0.3],[0.23,0.3],[0.15,0.3],[0,0],[-0.15,-0.3],[-0.15,-0.3],[-0.15,-0.23],[-0.15,-0.23],[-0.07,0],[-0.07,0],[0,0],[0,0],[0,0],[0,0],[0.38,-0.07],[0.45,-0.07],[0,0]],"v":[[294.6,23.93],[297.3,24.6],[298.2,26.55],[296.55,28.8],[297.07,29.48],[297.68,30.3],[298.28,31.2],[298.73,32.1],[297.08,32.1],[296.63,31.27],[296.11,30.45],[295.58,29.7],[295.13,29.02],[294.83,29.02],[294.61,29.02],[293.86,29.02],[293.86,32.1],[292.36,32.1],[292.35,24.15],[293.48,24],[294.6,23.93]],"c":true}}},{"ty":"sh","ks":{"k":{"i":[[0,0],[0.3,0],[0,0],[0,0],[-0.3,0.07],[-0.15,0.15],[-0.15,0.15],[0,0.3],[0.07,0.15],[0.15,0.07],[0.23,0.08],[0.3,0]],"o":[[-0.3,0],[0,0],[0,0],[0.38,0],[0.3,-0.07],[0.15,-0.07],[0.07,-0.15],[0,-0.23],[-0.07,-0.15],[-0.15,-0.07],[-0.3,0],[0,0]],"v":[[294.68,25.2],[293.78,25.2],[293.78,27.82],[294.45,27.82],[295.43,27.75],[296.11,27.52],[296.55,27.15],[296.7,26.47],[296.55,25.87],[296.18,25.5],[295.58,25.27],[294.68,25.2]],"c":true}}},{"ty":"fl","o":{"k":100},"c":{"k":[1,1,1,1]}},{"ty":"tr","o":{"k":100},"r":{"k":0},"p":{"k":[0,0]},"a":{"k":[0,0]},"s":{"k":[100,100]},"sk":{"k":0},"sa":{"k":0},"hd":false}]},{"ty":"gr","hd":false,"it":[{"ty":"sh","ks":{"k":{"i":[[0,0],[-0.6,-0.45],[0,-0.9],[0.15,-0.3],[0.3,-0.22],[0.45,-0.07],[0.6,0],[0,0],[0,0],[0,0],[0,0],[-0.38,0],[-0.38,0]],"o":[[1.2,0],[0.6,0.45],[0,0.45],[-0.15,0.38],[-0.3,0.23],[-0.45,0.07],[0,0],[0,0],[0,0],[0,0],[0.38,-0.07],[0.45,-0.07],[0,0]],"v":[[287.32,23.93],[290.02,24.6],[291,26.62],[290.77,27.82],[290.02,28.65],[288.82,29.1],[287.25,29.25],[286.5,29.25],[286.5,32.1],[285,32.1],[285,24.15],[286.12,24],[287.32,23.93]],"c":true}}},{"ty":"sh","ks":{"k":{"i":[[0,0],[0.22,0],[0,0],[0,0],[-0.38,0.23],[0,0.52],[0.07,0.15],[0.22,0.15],[0.3,0.08],[0.3,0]],"o":[[-0.38,0],[0,0],[0,0],[0.75,0],[0.38,-0.23],[0,-0.3],[-0.07,-0.15],[-0.23,-0.15],[-0.23,0.08],[0,0]],"v":[[287.4,25.2],[286.5,25.2],[286.5,27.97],[287.25,27.97],[288.9,27.67],[289.5,26.55],[289.35,25.87],[288.9,25.42],[288.23,25.2],[287.4,25.2]],"c":true}}},{"ty":"fl","o":{"k":100},"c":{"k":[1,1,1,1]}},{"ty":"tr","o":{"k":100},"r":{"k":0},"p":{"k":[0,0]},"a":{"k":[0,0]},"s":{"k":[100,100]},"sk":{"k":0},"sa":{"k":0},"hd":false}]},{"ty":"gr","hd":false,"it":[{"ty":"sh","ks":{"k":{"i":[[0,0],[-0.6,-0.45],[0,-0.82],[1.12,-0.38],[-0.22,-0.3],[-0.23,-0.3],[-0.23,-0.3],[-0.07,-0.3],[0,0],[0.15,0.22],[0.15,0.22],[0.15,0.23],[0.15,0.23],[0.07,0],[0.08,0],[0,0],[0,0],[0,0],[0,0],[-0.38,0],[-0.3,0]],"o":[[1.2,0],[0.6,0.45],[0,1.12],[0.15,0.15],[0.23,0.3],[0.23,0.3],[0.15,0.3],[0,0],[-0.15,-0.3],[-0.15,-0.3],[-0.15,-0.23],[-0.15,-0.23],[-0.07,0],[-0.07,0],[0,0],[0,0],[0,0],[0,0],[0.38,-0.07],[0.45,-0.07],[0,0]],"v":[[276.98,23.93],[279.68,24.6],[280.57,26.55],[278.93,28.8],[279.45,29.48],[280.05,30.3],[280.65,31.2],[281.1,32.1],[279.45,32.1],[279,31.27],[278.48,30.45],[277.96,29.7],[277.51,29.02],[277.21,29.02],[276.98,29.02],[276.23,29.02],[276.23,32.1],[274.73,32.1],[274.73,24.15],[275.85,24],[276.98,23.93]],"c":true}}},{"ty":"sh","ks":{"k":{"i":[[0,0],[0.3,0],[0,0],[0,0],[-0.3,0.07],[-0.15,0.15],[-0.15,0.15],[0,0.3],[0.07,0.15],[0.15,0.07],[0.23,0.08],[0.3,0]],"o":[[-0.3,0],[0,0],[0,0],[0.38,0],[0.3,-0.07],[0.15,-0.07],[0.07,-0.15],[0,-0.23],[-0.07,-0.15],[-0.15,-0.07],[-0.38,0],[0,0]],"v":[[277.12,25.2],[276.23,25.2],[276.23,27.82],[276.9,27.82],[277.88,27.75],[278.55,27.52],[279,27.15],[279.15,26.47],[279,25.87],[278.63,25.5],[278.03,25.27],[277.12,25.2]],"c":true}}},{"ty":"fl","o":{"k":100},"c":{"k":[1,1,1,1]}},{"ty":"tr","o":{"k":100},"r":{"k":0},"p":{"k":[0,0]},"a":{"k":[0,0]},"s":{"k":[100,100]},"sk":{"k":0},"sa":{"k":0},"hd":false}]},{"ty":"gr","hd":false,"it":[{"ty":"sh","ks":{"k":{"i":[[0,0],[0.23,-0.6],[0.3,-0.38],[0.52,-0.22],[0.52,0],[0.45,0.23],[0.38,0.38],[0.15,0.53],[0,0.75],[-0.23,0.6],[-0.38,0.38],[-0.52,0.22],[-0.52,0],[-0.45,-0.23],[-0.38,-0.38],[-0.15,-0.53],[0,-0.68]],"o":[[0,0.68],[-0.23,0.52],[-0.38,0.38],[-0.45,0.15],[-0.52,0],[-0.45,-0.23],[-0.38,-0.38],[-0.23,-0.52],[0,-0.75],[0.23,-0.52],[0.38,-0.38],[0.45,-0.15],[0.52,0],[0.45,0.15],[0.38,0.38],[0.08,0.6],[0,0]],"v":[[273.15,28.05],[272.85,29.93],[272.02,31.28],[270.75,32.1],[269.25,32.4],[267.75,32.1],[266.48,31.28],[265.65,29.93],[265.35,28.05],[265.65,26.18],[266.55,24.82],[267.82,24],[269.32,23.7],[270.82,24],[272.1,24.82],[272.92,26.18],[273.15,28.05]],"c":true}}},{"ty":"sh","ks":{"k":{"i":[[0,0],[-0.07,-0.38],[-0.15,-0.22],[-0.3,-0.15],[-0.38,0],[-0.3,0.15],[-0.23,0.23],[-0.07,0.3],[0,0.45],[0.07,0.38],[0.15,0.22],[0.3,0.15],[0.38,0],[0.23,-0.15],[0.23,-0.23],[0.07,-0.3],[0,-0.38]],"o":[[0,0.45],[0.07,0.38],[0.23,0.23],[0.3,0.15],[0.38,0],[0.3,-0.15],[0.23,-0.23],[0.07,-0.3],[0,-0.45],[-0.07,-0.38],[-0.23,-0.23],[-0.3,-0.15],[-0.38,0],[-0.3,0.15],[-0.23,0.23],[-0.07,0.3],[0,0]],"v":[[266.77,28.05],[266.92,29.25],[267.37,30.15],[268.12,30.75],[269.1,30.98],[270.07,30.75],[270.82,30.15],[271.27,29.25],[271.42,28.05],[271.27,26.85],[270.82,25.95],[270.07,25.35],[269.1,25.12],[268.12,25.35],[267.37,25.95],[266.92,26.85],[266.77,28.05]],"c":true}}},{"ty":"fl","o":{"k":100},"c":{"k":[1,1,1,1]}},{"ty":"tr","o":{"k":100},"r":{"k":0},"p":{"k":[0,0]},"a":{"k":[0,0]},"s":{"k":[100,100]},"sk":{"k":0},"sa":{"k":0},"hd":false}]},{"ty":"gr","hd":false,"it":[{"ty":"sh","ks":{"k":{"i":[[0,0],[0,0],[0,0],[0,0],[0,0],[0,0],[0,0],[0,0]],"o":[[0,0],[0,0],[0,0],[0,0],[0,0],[0,0],[0,0],[0,0]],"v":[[264.45,24],[264.45,25.27],[261.97,25.27],[261.97,32.17],[260.47,32.17],[260.47,25.27],[258,25.27],[258,24]],"c":true}}},{"ty":"fl","o":{"k":100},"c":{"k":[1,1,1,1]}},{"ty":"tr","o":{"k":100},"r":{"k":0},"p":{"k":[0,0]},"a":{"k":[0,0]},"s":{"k":[100,100]},"sk":{"k":0},"sa":{"k":0},"hd":false}]},{"ty":"gr","hd":false,"it":[{"ty":"sh","ks":{"k":{"i":[[0,0],[0,0],[0,0],[0,0],[0,0],[0,0],[0,0],[0,0],[0,0],[0,0],[0,0],[0,0]],"o":[[0,0],[0,0],[0,0],[0,0],[0,0],[0,0],[0,0],[0,0],[0,0],[0,0],[0,0],[0,0]],"v":[[251.85,32.18],[251.85,24],[257.1,24],[257.1,25.27],[253.35,25.27],[253.35,27.3],[256.73,27.3],[256.73,28.5],[253.35,28.5],[253.35,30.9],[257.4,30.9],[257.4,32.17]],"c":true}}},{"ty":"fl","o":{"k":100},"c":{"k":[1,1,1,1]}},{"ty":"tr","o":{"k":100},"r":{"k":0},"p":{"k":[0,0]},"a":{"k":[0,0]},"s":{"k":[100,100]},"sk":{"k":0},"sa":{"k":0},"hd":false}]},{"ty":"gr","hd":false,"it":[{"ty":"sh","ks":{"k":{"i":[[0,0],[-0.3,0.23],[0,0.3],[0.07,0.15],[0.15,0.07],[0.15,0.07],[0.3,0.07],[0.3,0.07],[0.15,0.15],[0.07,0.3],[0,0.38],[-0.52,0.38],[-0.9,0],[-0.38,-0.07],[-0.22,-0.15],[0,0],[0.38,0.07],[0.3,0],[0.22,-0.15],[0,-0.3],[-0.07,-0.15],[-0.15,-0.15],[-0.15,-0.07],[-0.23,-0.08],[-0.3,-0.15],[-0.23,-0.22],[-0.07,-0.23],[0,-0.38],[0.52,-0.45],[0.98,0],[0.22,0.07],[0.23,0.07],[0.15,0.08],[0.07,0],[0,0],[-0.3,-0.15],[-0.52,0]],"o":[[0.52,0],[0.23,-0.15],[0,-0.23],[-0.07,-0.15],[-0.15,-0.15],[-0.23,-0.07],[-0.3,-0.07],[-0.3,-0.07],[-0.23,-0.15],[-0.15,-0.23],[0,-0.75],[0.52,-0.45],[0.52,0],[0.38,0.15],[0,0],[-0.3,-0.15],[-0.3,-0.07],[-0.38,0],[-0.23,0.15],[0,0.15],[0.07,0.15],[0.15,0.07],[0.15,0.07],[0.38,0.15],[0.3,0.15],[0.23,0.23],[0.07,0.23],[0,0.75],[-0.52,0.45],[-0.3,0],[-0.3,-0.07],[-0.23,-0.07],[-0.15,-0.07],[0,0],[0.23,0.15],[0.29,0.14],[0,0]],"v":[[247.5,31.05],[248.7,30.75],[249.07,30],[248.93,29.48],[248.55,29.1],[248.03,28.8],[247.28,28.5],[246.45,28.2],[245.78,27.75],[245.33,27.07],[245.18,26.18],[245.93,24.45],[248.03,23.85],[249.38,24],[250.28,24.37],[249.83,25.57],[248.93,25.2],[247.96,25.05],[247.06,25.27],[246.76,25.95],[246.83,26.4],[247.13,26.77],[247.58,27.07],[248.18,27.3],[249.23,27.75],[249.98,28.27],[250.43,28.95],[250.58,29.93],[249.83,31.65],[247.58,32.25],[246.68,32.18],[245.93,32.03],[245.41,31.8],[245.04,31.66],[245.48,30.46],[246.31,30.83],[247.5,31.05]],"c":true}}},{"ty":"fl","o":{"k":100},"c":{"k":[1,1,1,1]}},{"ty":"tr","o":{"k":100},"r":{"k":0},"p":{"k":[0,0]},"a":{"k":[0,0]},"s":{"k":[100,100]},"sk":{"k":0},"sa":{"k":0},"hd":false}]},{"ty":"gr","hd":false,"it":[{"ty":"sh","ks":{"k":{"i":[[0,0],[0.82,0.75],[0.45,0.98],[1.27,5.4],[0,0],[2.62,4.88],[4.65,1.8],[1.88,0.38],[0.38,0],[0.98,0.22],[0.08,0.07],[0.45,0.9],[-0.15,0.3],[-0.53,0.23],[-0.15,0.08],[-2.7,-0.15],[-2.48,-0.9],[-3.07,-4.73],[-1.35,-4.95],[-0.97,-2.55],[-0.6,0.15],[-0.23,0.68],[0,0],[-0.98,1.05],[-1.43,-0.6],[-0.15,-1.57],[0.3,-1.05],[5.85,-13.95],[1.8,-0.6],[0.3,0]],"o":[[-0.98,0],[-0.9,-0.82],[-2.4,-5.18],[0,0],[-1.43,-6.07],[-2.93,-5.55],[-2.02,-0.82],[-0.38,-0.07],[-0.9,-0.15],[-0.07,0],[-0.6,-0.07],[-0.15,-0.38],[0.15,-0.38],[0.23,-0.07],[2.55,-0.68],[2.62,0.15],[5.25,1.95],[2.85,4.43],[0.75,2.62],[0.38,1.05],[0.45,-0.15],[0,0],[0.38,-1.2],[1.2,-1.35],[1.2,0.52],[0.07,1.27],[-4.12,13.65],[-0.45,1.05],[-0.38,0.08],[0,0]],"v":[[224.7,69.75],[221.93,68.62],[220.05,65.77],[215.03,49.57],[214.88,48.9],[209.48,32.55],[197.71,21.07],[191.56,19.5],[190.51,19.35],[187.66,18.82],[187.43,18.75],[185.33,17.62],[185.25,16.57],[186.3,15.6],[186.91,15.37],[194.78,14.55],[202.51,16.12],[215.41,26.47],[221.03,40.95],[223.43,48.82],[225.08,50.7],[226.05,49.12],[235.36,21.75],[237.23,18.15],[241.66,16.95],[243.83,20.4],[243.23,23.92],[228.68,66.07],[225.68,69.59],[224.7,69.75]],"c":true}}},{"ty":"sh","ks":{"k":{"i":[[0,0],[-0.82,-0.15],[-0.38,0],[-2.17,-0.82],[-3.15,-6],[-1.5,-6.15],[0,0],[-2.32,-4.95],[-0.6,-0.6],[-0.52,0.15],[-0.38,1.05],[-4.12,13.57],[0.08,0.9],[0.68,0.3],[0.52,-0.68],[0.3,-1.05],[0,0],[1.5,-0.38],[0.82,2.32],[0.75,2.7],[2.62,4.2],[4.88,1.8],[2.48,0.07],[2.03,-0.45]],"o":[[0.82,0.15],[0.38,0.07],[2.02,0.38],[5.1,2.02],[2.7,5.1],[0,0],[1.27,5.32],[0.38,0.75],[0.6,0.52],[0.9,-0.3],[5.77,-13.88],[0.3,-0.9],[-0.07,-0.68],[-0.75,-0.3],[-0.75,0.75],[0,0],[-0.3,0.75],[-1.57,0.38],[-0.98,-2.62],[-1.35,-5.02],[-2.85,-4.35],[-2.25,-0.82],[-2.25,-0.07],[0,0]],"v":[[188.32,17.02],[190.72,17.47],[191.77,17.62],[198.3,19.27],[211.12,31.64],[216.67,48.45],[216.82,49.12],[221.7,64.95],[223.12,67.2],[225,67.8],[226.8,65.4],[241.27,23.4],[241.8,20.62],[240.75,18.82],[238.5,19.57],[237.07,22.5],[227.77,49.88],[225.45,52.65],[221.55,49.57],[219.07,41.47],[213.75,27.52],[201.82,17.92],[194.7,16.5],[188.32,17.02]],"c":true}}},{"ty":"fl","o":{"k":100},"c":{"k":[1,1,1,1]}},{"ty":"tr","o":{"k":100},"r":{"k":0},"p":{"k":[0,0]},"a":{"k":[0,0]},"s":{"k":[100,100]},"sk":{"k":0},"sa":{"k":0},"hd":false}]},{"ty":"gr","hd":false,"it":[{"ty":"sh","ks":{"k":{"i":[[0,0],[-0.23,-0.38],[-0.52,-0.07],[-1.27,-0.23],[-2.02,-0.75],[-2.7,-5.18],[-1.35,-5.7],[-2.48,-5.33],[-0.75,-0.68],[-0.97,0.23],[-0.45,1.2],[-4.28,14.25],[0.08,1.05],[0.97,0.45],[0.9,-0.98],[0.38,-1.2],[3.07,-9.15],[0.9,-0.23],[0.45,1.28],[4.27,6.6],[5.1,1.88],[2.55,0.15],[2.47,-0.6],[0.15,-0.07]],"o":[[-0.3,0.15],[0.3,0.52],[1.27,0.23],[2.18,0.38],[5.4,2.1],[2.7,5.18],[1.35,5.7],[0.45,0.9],[0.75,0.68],[1.27,-0.38],[5.7,-13.73],[0.3,-1.05],[-0.07,-1.05],[-1.12,-0.52],[-0.82,0.9],[-3.07,9.15],[-0.3,0.9],[-1.35,0.38],[-2.7,-7.43],[-2.93,-4.57],[-2.4,-0.9],[-2.55,-0.15],[-0.08,-0.08],[0,0]],"v":[[186.6,16.5],[186.15,17.25],[187.8,17.93],[191.62,18.6],[198,20.18],[210.3,32.1],[215.78,48.68],[220.88,65.4],[222.53,67.95],[225.3,68.78],[227.7,65.85],[242.18,23.78],[242.7,20.63],[241.12,18],[237.75,18.98],[236.1,22.28],[226.8,49.66],[225.15,51.83],[222.38,49.36],[214.5,27.16],[202.05,17.18],[194.63,15.68],[187.05,16.43],[186.6,16.5]],"c":true}}},{"ty":"fl","o":{"k":100},"c":{"k":[1,1,1,1]}},{"ty":"tr","o":{"k":100},"r":{"k":0},"p":{"k":[0,0]},"a":{"k":[0,0]},"s":{"k":[100,100]},"sk":{"k":0},"sa":{"k":0},"hd":false}]},{"ty":"gr","hd":false,"it":[{"ty":"sh","ks":{"k":{"i":[[0,0],[0,13.57],[-13.57,0],[0,-13.65],[13.65,0]],"o":[[-13.65,0],[0,-13.57],[13.57,0],[0,13.65],[0,0]],"v":[[183.82,70.88],[159.15,46.2],[183.82,21.52],[208.5,46.2],[183.82,70.88]],"c":true}}},{"ty":"sh","ks":{"k":{"i":[[0,0],[0,-13.58],[-13.58,0],[0,13.58],[13.57,0]],"o":[[-13.57,0],[0,13.57],[13.57,0],[0,-13.58],[0,0]],"v":[[183.82,21.6],[159.22,46.2],[183.82,70.8],[208.43,46.2],[183.82,21.6]],"c":true}}},{"ty":"sh","ks":{"k":{"i":[[0,0],[0,8.47],[-8.47,0],[0,-8.47],[8.55,0]],"o":[[-8.55,0],[0,-8.48],[8.55,0],[0,8.47],[0,0]],"v":[[184.27,61.35],[168.82,45.9],[184.27,30.45],[199.72,45.9],[184.27,61.35]],"c":true}}},{"ty":"sh","ks":{"k":{"i":[[0,0],[0,-8.4],[-8.4,0],[0,8.4],[8.48,0]],"o":[[-8.48,0],[0,8.4],[8.48,0],[0,-8.4],[0,0]],"v":[[184.27,30.52],[168.97,45.82],[184.27,61.12],[199.57,45.82],[184.27,30.52]],"c":true}}},{"ty":"fl","o":{"k":100},"c":{"k":[1,1,1,1]}},{"ty":"tr","o":{"k":100},"r":{"k":0},"p":{"k":[0,0]},"a":{"k":[0,0]},"s":{"k":[100,100]},"sk":{"k":0},"sa":{"k":0},"hd":false}]},{"ty":"gr","hd":false,"it":[{"ty":"sh","ks":{"k":{"i":[[0,0],[0,-13.65],[-13.65,0],[0,13.57],[13.57,0]],"o":[[-13.57,0],[0,13.57],[13.65,0],[0,-13.65],[0,0]],"v":[[183.82,21.52],[159.15,46.2],[183.82,70.88],[208.5,46.2],[183.82,21.52]],"c":true}}},{"ty":"sh","ks":{"k":{"i":[[0,0],[0,8.48],[-8.48,0],[0,-8.48],[8.48,0]],"o":[[-8.48,0],[0,-8.48],[8.48,0],[0,8.48],[0,0]],"v":[[184.27,61.27],[168.9,45.9],[184.27,30.52],[199.65,45.9],[184.27,61.27]],"c":true}}},{"ty":"fl","o":{"k":100},"c":{"k":[1,1,1,1]}},{"ty":"tr","o":{"k":100},"r":{"k":0},"p":{"k":[0,0]},"a":{"k":[0,0]},"s":{"k":[100,100]},"sk":{"k":0},"sa":{"k":0},"hd":false}]},{"ty":"gr","hd":false,"it":[{"ty":"sh","ks":{"k":{"i":[[0,0],[2.78,0.9],[2.62,5.02],[-0.08,5.93],[0,0],[0,0.45],[4.88,2.7],[3.23,-3],[-0.15,-4.42],[0,-0.82],[0,0],[4.65,-4.43],[3,-0.45],[2.62,1.35],[1.2,3],[0,3.3],[0,3.83],[0,3.98],[-0.45,0.45],[-1.95,0],[0,0],[-0.9,-0.98],[0,-0.75],[0,-3.75],[0.07,-2.25],[0,-0.45],[-2.77,-1.88],[-1.57,0.68],[0.07,2.4],[0,0],[-0.22,3.68],[-5.32,4.12],[-5.47,-0.3],[-2.7,-6.38],[0.15,-5.62],[-0.07,-2.1],[-4.95,-3.68],[-3.53,-0.97],[-1.88,-0.23],[-0.07,-0.52],[0.68,-0.23],[1.8,0]],"o":[[-3.9,0],[-5.93,-1.95],[-2.85,-5.48],[0,0],[0,-0.38],[0.07,-4.95],[-3.75,-2.1],[-3.38,3],[0,0.9],[0,0],[0,5.93],[-2.1,2.02],[-3,0.45],[-2.55,-1.35],[-0.98,-2.4],[0,-3.38],[0,-4.5],[0,-1.2],[0.68,-0.68],[0,0],[1.2,0],[0.38,0.45],[-0.07,1.65],[0,4.2],[0,0.3],[-0.07,3.3],[0.98,0.68],[3.07,-1.35],[0,0],[0,-3.68],[0.3,-5.25],[4.43,-3.45],[5.7,0.3],[2.18,5.1],[-0.07,2.1],[0.23,6],[2.85,2.1],[1.73,0.45],[0.75,0.07],[0,0.52],[-1.79,0.14],[0,0]],"v":[[174.45,76.5],[164.02,74.85],[150.52,63.83],[147.75,46.35],[147.75,45.83],[147.75,44.63],[143.02,30.9],[130.05,32.55],[126.97,45.07],[127.05,47.62],[127.05,47.93],[122.32,65.03],[114.52,68.78],[105.97,67.35],[100.34,60.83],[98.84,52.2],[98.84,41.1],[98.84,27.98],[99.52,25.58],[103.42,24.9],[103.87,24.9],[107.84,25.88],[108.45,27.61],[108.37,36.46],[108.3,47.18],[108.3,48.31],[110.7,60.38],[114.52,60.31],[117.52,52.58],[117.52,51.98],[117.67,40.8],[123.97,25.43],[139.49,20.55],[155.02,29.86],[156.82,46.36],[156.74,52.8],[164.77,67.88],[174.37,72.53],[179.77,73.58],[180.96,74.78],[179.99,76.13],[174.45,76.5]],"c":true}}},{"ty":"sh","ks":{"k":{"i":[[0,0],[-1.5,-0.82],[0.07,-4.95],[0,-0.38],[0,0],[-2.85,-5.4],[-5.93,-1.95],[-5.55,1.27],[0,0.52],[0.68,0.07],[0,0],[1.65,0.53],[2.85,2.1],[0.23,6.08],[-0.07,2.18],[2.18,5.1],[5.7,0.3],[4.35,-3.45],[0.38,-6.68],[0,-3.68],[0,0],[3.22,-1.43],[1.05,0.68],[-0.15,3.3],[0,0.3],[0,4.2],[-0.07,1.65],[0.38,0.38],[1.2,0],[0,0],[0.68,-0.68],[0,-1.2],[0,-4.5],[0,-3.45],[-6.07,-3.23],[-4.27,4.05],[0,5.92],[0,0],[0.07,0.9],[-3.45,3.08],[-2.93,0]],"o":[[1.8,0],[4.95,2.7],[0,0.38],[0,0],[0,5.85],[2.62,5.02],[4.05,1.35],[0.68,-0.15],[0,-0.45],[0,0],[-1.88,-0.23],[-3.52,-0.98],[-5.02,-3.75],[-0.07,-2.1],[0.23,-5.55],[-2.7,-6.3],[-5.4,-0.3],[-4.8,3.75],[-0.23,3.75],[0,0],[0,2.4],[-1.57,0.75],[-2.85,-1.88],[0,-0.45],[0.07,-2.25],[0,-3.75],[0,-0.68],[-0.9,-0.9],[0,0],[-1.88,0],[-0.45,0.45],[0,3.98],[0,3.75],[0,4.2],[5.18,2.77],[4.65,-4.43],[0,0],[0,-0.82],[-0.15,-4.5],[2.18,-1.95],[0,0]],"v":[[138,29.62],[143.1,30.82],[147.9,44.62],[147.9,45.82],[147.9,46.35],[150.68,63.75],[164.1,74.7],[180,75.75],[180.9,74.55],[179.85,73.5],[179.77,73.5],[174.38,72.45],[164.77,67.8],[156.67,52.57],[156.75,46.12],[154.95,29.7],[139.5,20.47],[124.12,25.34],[117.82,40.64],[117.67,51.82],[117.67,52.42],[114.52,60.3],[110.55,60.37],[108.07,48.22],[108.07,47.1],[108.14,36.37],[108.22,27.52],[107.7,25.95],[103.8,25.05],[103.35,25.05],[99.52,25.72],[98.92,28.05],[98.92,41.17],[98.92,52.27],[105.97,67.27],[122.1,65.02],[126.75,48],[126.75,47.7],[126.67,45.15],[129.82,32.55],[138,29.62]],"c":true}}},{"ty":"fl","o":{"k":100},"c":{"k":[1,1,1,1]}},{"ty":"tr","o":{"k":100},"r":{"k":0},"p":{"k":[0,0]},"a":{"k":[0,0]},"s":{"k":[100,100]},"sk":{"k":0},"sa":{"k":0},"hd":false}]},{"ty":"gr","hd":false,"it":[{"ty":"sh","ks":{"k":{"i":[[0,0],[1.35,-0.38],[4.57,1.5],[2.78,5.32],[0,6.15],[5.25,2.93],[3.23,-2.92],[0.07,-4.88],[4.73,-4.5],[5.32,2.85],[0.07,5.7],[0,7.35],[-3.38,0],[0.15,-2.7],[0.22,-4.2],[-7.5,3.38],[0,2.78],[-0.22,3.9],[-5.03,3.9],[-5.47,-0.3],[-2.55,-6],[-0.23,-7.43],[-5.03,-3.67],[-3.45,-0.97],[-1.88,-0.15]],"o":[[1.35,0.15],[-5.18,1.2],[-5.62,-1.88],[-2.93,-5.62],[0,-5.1],[-3.82,-2.1],[-4.05,3.68],[0,6],[-4.27,4.12],[-5.55,-2.93],[0,-7.43],[0,-3.07],[1.65,0],[-0.15,3.38],[-0.07,3.45],[3,-1.35],[0,-3.9],[0.3,-6],[4.35,-3.38],[6.3,0.38],[3,7.12],[0.23,6.15],[2.85,2.1],[1.8,0.38],[0,0]],"v":[[179.77,73.43],[179.92,75.82],[164.02,74.77],[150.6,63.75],[147.82,45.82],[143.1,30.9],[130.05,32.55],[126.97,47.7],[122.25,65.02],[106.05,67.27],[98.92,52.2],[98.92,28.05],[103.65,25.05],[108.3,27.67],[108.15,47.17],[114.45,60.3],[117.52,52.5],[117.67,40.72],[123.97,25.42],[139.42,20.55],[154.87,29.85],[156.6,52.72],[164.7,67.87],[174.3,72.52],[179.77,73.43]],"c":true}}},{"ty":"fl","o":{"k":100},"c":{"k":[1,1,1,1]}},{"ty":"tr","o":{"k":100},"r":{"k":0},"p":{"k":[0,0]},"a":{"k":[0,0]},"s":{"k":[100,100]},"sk":{"k":0},"sa":{"k":0},"hd":false}]},{"ty":"gr","hd":false,"it":[{"ty":"sh","ks":{"k":{"i":[[0,0],[0,2.62],[-2.62,0],[0,-2.62],[2.62,0]],"o":[[-2.62,0],[0,-2.62],[2.62,0],[0,2.63],[0,0]],"v":[[103.57,21.9],[98.85,17.17],[103.57,12.45],[108.3,17.17],[103.57,21.9]],"c":true}}},{"ty":"sh","ks":{"k":{"i":[[0,0],[0,-2.55],[-2.55,0],[0,2.55],[2.55,0]],"o":[[-2.55,0],[0,2.55],[2.55,0],[0,-2.55],[0,0]],"v":[[103.57,12.6],[99,17.18],[103.57,21.75],[108.15,17.18],[103.57,12.6]],"c":true}}},{"ty":"fl","o":{"k":100},"c":{"k":[1,1,1,1]}},{"ty":"tr","o":{"k":100},"r":{"k":0},"p":{"k":[0,0]},"a":{"k":[0,0]},"s":{"k":[100,100]},"sk":{"k":0},"sa":{"k":0},"hd":false}]},{"ty":"gr","hd":false,"it":[{"ty":"sh","ks":{"k":{"i":[[0,0],[0,6.2],[0,-6.2]],"o":[[0,6.2],[0,-6.2],[0,0]],"v":[[108.23,17.18],[98.93,17.18],[108.23,17.18]],"c":false}}},{"ty":"fl","o":{"k":100},"c":{"k":[1,1,1,1]}},{"ty":"tr","o":{"k":100},"r":{"k":0},"p":{"k":[0,0]},"a":{"k":[0,0]},"s":{"k":[100,100]},"sk":{"k":0},"sa":{"k":0},"hd":false}]},{"ty":"tr","o":{"k":100},"r":{"k":0},"p":{"k":[0,0]},"a":{"k":[0,0]},"s":{"k":[100,100]},"sk":{"k":0},"sa":{"k":0},"hd":false}]}]}],"meta":{"g":"LF SVG to Lottie"},"assets":[]}